rax_instance_backup_python_novaclient_ext
