Metadata-Version: 1.0
Name: rax-instance-backup-python-novaclient-ext
Version: 0.1.2
Summary: Novaclient Extension for Instance Backups
Home-page: https://github.com/rackspace/rax_instance_backup_python_novaclient_ext
Author: Rackspace
Author-email: rick.harris@rackspace.com
License: Apache License, Version 2.0
Platform: UNKNOWN
Classifier: Development Status :: 5 - Production/Stable
Classifier: Intended Audience :: Developers
Classifier: Intended Audience :: Information Technology
Classifier: License :: OSI Approved :: Apache Software License
Classifier: Operating System :: OS Independent
Classifier: Programming Language :: Python
